inheritson/__init__.py
inheritson/inheritson.py
inheritson-0.0.3.dist-info/LICENSE
inheritson-0.0.3.dist-info/METADATA
inheritson-0.0.3.dist-info/WHEEL
inheritson-0.0.3.dist-info/top_level.txt
inheritson-0.0.3.dist-info/RECORD
